nias/__init__.py
nias/exceptions.py
nias/interfaces.py
nias/base/__init__.py
nias/base/linear_solvers.py
nias/base/operators.py
nias/base/vectorarrays.py
nias/bindings/__init__.py
nias/bindings/numpy/__init__.py
nias/bindings/numpy/linear_solvers.py
nias/bindings/numpy/operators.py
nias/bindings/numpy/vectorarrays.py
nias/linalg/__init__.py
nias/linalg/eigs.py
nias/linalg/gram_schmidt.py
nias/linalg/svd.py
nias-0.0.2.dist-info/METADATA
nias-0.0.2.dist-info/WHEEL
nias-0.0.2.dist-info/licenses/LICENSE.txt
nias-0.0.2.dist-info/RECORD
