Metadata-Version: 2.3
Name: nias
Version: 0.0.2
Summary: Numerics In Abstract Spaces
Author-email: NIAS developers <main.developers@pymor.org>
Maintainer-email: Stephan Rave <stephan.rave@uni-muenster.de>
License: Copyright NIAS developers and contributors. All rights reserved.
License-File: LICENSE.txt
Classifier: Intended Audience :: Science/Research
Classifier: License :: OSI Approved :: BSD License
Classifier: Programming Language :: Python :: 3.8
Classifier: Programming Language :: Python :: 3.9
Classifier: Programming Language :: Python :: 3.10
Classifier: Programming Language :: Python :: 3.11
Classifier: Topic :: Scientific/Engineering :: Mathematics
Requires-Python: >=3.8
Requires-Dist: numpy!=1.25.0,<2,>=1.20.3
Requires-Dist: scipy>=1.5.4
Requires-Dist: typer
Provides-Extra: docs
Requires-Dist: myst-nb; extra == 'docs'
Requires-Dist: sphinx; extra == 'docs'
Provides-Extra: tests
Requires-Dist: pytest-cov; extra == 'tests'
Requires-Dist: pytest>=7.2.1; extra == 'tests'
